AxmlParserPY-0.0.3.dist-info/DESCRIPTION.rst
AxmlParserPY-0.0.3.dist-info/METADATA
AxmlParserPY-0.0.3.dist-info/RECORD
AxmlParserPY-0.0.3.dist-info/WHEEL
AxmlParserPY-0.0.3.dist-info/metadata.json
AxmlParserPY-0.0.3.dist-info/top_level.txt
axmlparserpy/__init__.py
axmlparserpy/apk.py
axmlparserpy/axmlparser.py
axmlparserpy/axmlprinter.py
axmlparserpy/bytecode.py
axmlparserpy/stringblock.py
axmlparserpy/typeconstants.py
