Metadata-Version: 2.0
Name: AxmlParserPY
Version: 0.0.3
Summary: Python support for extract information from android 'apk' package
Home-page: https://github.com/kzjeef/AxmlParserPY.git
Author: Anthony Desnos
Author-email: anthony.desnos@gmail.com
License: UNKNOWN
Platform: UNKNOWN
